{
"type": "FeatureCollection",
"name": "FULL VIBWETA",
"crs": { "type": "name", "properties": { "name": "urn:ogc:def:crs:OGC:1.3:CRS84" } },
"features": [
{ "type": "Feature", "properties": { "FID": 0 }, "geometry": { "type": "Point", "coordinates": [ 39.240198753873912, -6.772162563984455 ] } },
{ "type": "Feature", "properties": { "FID": 1 }, "geometry": { "type": "Point", "coordinates": [ 39.240188423776949, -6.772150727803883 ] } },
{ "type": "Feature", "properties": { "FID": 2 }, "geometry": { "type": "Point", "coordinates": [ 39.240191602268318, -6.772140469780483 ] } },
{ "type": "Feature", "properties": { "FID": 3 }, "geometry": { "type": "Point", "coordinates": [ 39.240203521610979, -6.772141258859214 ] } },
{ "type": "Feature", "properties": { "FID": 4 }, "geometry": { "type": "Point", "coordinates": [ 39.240209878593731, -6.772146782410293 ] } },
{ "type": "Feature", "properties": { "FID": 5 }, "geometry": { "type": "Point", "coordinates": [ 39.240209083970896, -6.772159407669665 ] } },
{ "type": "Feature", "properties": { "FID": 6 }, "geometry": { "type": "Point", "coordinates": [ 39.239977848723285, -6.771813001995829 ] } },
{ "type": "Feature", "properties": { "FID": 7 }, "geometry": { "type": "Point", "coordinates": [ 39.239984205706044, -6.771806689361651 ] } },
{ "type": "Feature", "properties": { "FID": 8 }, "geometry": { "type": "Point", "coordinates": [ 39.239941296072466, -6.771732515903889 ] } },
{ "type": "Feature", "properties": { "FID": 9 }, "geometry": { "type": "Point", "coordinates": [ 39.239932555221188, -6.771739617618423 ] } },
{ "type": "Feature", "properties": { "FID": 10 }, "geometry": { "type": "Point", "coordinates": [ 39.239947653055225, -6.771777493427511 ] } },
{ "type": "Feature", "properties": { "FID": 11 }, "geometry": { "type": "Point", "coordinates": [ 39.239922225124211, -6.771785384220695 ] } },
{ "type": "Feature", "properties": { "FID": 12 }, "geometry": { "type": "Point", "coordinates": [ 39.239935733712556, -6.771793275013751 ] } },
{ "type": "Feature", "properties": { "FID": 13 }, "geometry": { "type": "Point", "coordinates": [ 39.239983411083195, -6.771715945236235 ] } },
{ "type": "Feature", "properties": { "FID": 14 }, "geometry": { "type": "Point", "coordinates": [ 39.239996125048698, -6.771726203268659 ] } },
{ "type": "Feature", "properties": { "FID": 15 }, "geometry": { "type": "Point", "coordinates": [ 39.240008044391359, -6.771755399205904 ] } },
{ "type": "Feature", "properties": { "FID": 16 }, "geometry": { "type": "Point", "coordinates": [ 39.239981821837517, -6.7717806497448 ] } },
{ "type": "Feature", "properties": { "FID": 17 }, "geometry": { "type": "Point", "coordinates": [ 39.23995177597422, -6.771692253071486 ] } },
{ "type": "Feature", "properties": { "FID": 18 }, "geometry": { "type": "Point", "coordinates": [ 39.240358556546894, -6.771378192710028 ] } },
{ "type": "Feature", "properties": { "FID": 19 }, "geometry": { "type": "Point", "coordinates": [ 39.24034151861715, -6.771367618283527 ] } },
{ "type": "Feature", "properties": { "FID": 20 }, "geometry": { "type": "Point", "coordinates": [ 39.240424578524667, -6.771360216184838 ] } },
{ "type": "Feature", "properties": { "FID": 21 }, "geometry": { "type": "Point", "coordinates": [ 39.240425643395277, -6.771390882021525 ] } },
{ "type": "Feature", "properties": { "FID": 22 }, "geometry": { "type": "Point", "coordinates": [ 39.240090209153401, -6.771149785046037 ] } },
{ "type": "Feature", "properties": { "FID": 23 }, "geometry": { "type": "Point", "coordinates": [ 39.240118960659842, -6.771175163680708 ] } },
{ "type": "Feature", "properties": { "FID": 24 }, "geometry": { "type": "Point", "coordinates": [ 39.240149841907503, -6.771132865955514 ] } },
{ "type": "Feature", "properties": { "FID": 25 }, "geometry": { "type": "Point", "coordinates": [ 39.240118960659842, -6.771117004307611 ] } }
]
}
